pspca/__init__.py
pspca/py.typed
pspca/utils.py
pspca/wrapper.py
pspca-0.0.1a2.dist-info/LICENSE.rst
pspca-0.0.1a2.dist-info/WHEEL
pspca-0.0.1a2.dist-info/METADATA
pspca-0.0.1a2.dist-info/RECORD
