Metadata-Version: 2.1
Name: pspca
Version: 0.0.1a2
Summary: Projective Space PCA
Home-page: https://github.com/gatoniel/pspca
License: MIT
Author: Niklas Netter
Author-email: niklas.netter@unibas.ch
Requires-Python: >=3.7.1,<3.10
Classifier: Development Status :: 1 - Planning
Classifier: License :: OSI Approved :: MIT License
Classifier: Programming Language :: Python :: 3
Classifier: Programming Language :: Python :: 3.6
Classifier: Programming Language :: Python :: 3.7
Classifier: Programming Language :: Python :: 3.8
Classifier: Programming Language :: Python :: 3.9
Requires-Dist: matplotlib (>=3.4.3,<4.0.0)
Requires-Dist: numpy (>=1.21.2,<2.0.0)
Requires-Dist: scipy (>=1.7.1,<2.0.0)
Project-URL: Changelog, https://github.com/gatoniel/pspca/releases
Project-URL: Documentation, https://pspca.readthedocs.io
Project-URL: Repository, https://github.com/gatoniel/pspca
